template_forge/__init__.py
template_forge/cli.py
template_forge/core.py
template_forge/extraction.py
template_forge/hooks.py
template_forge/preservation.py
template_forge/processing.py
template_forge/py.typed
template_forge/types.py
template_forge/utils.py
template_forge-1.0.0.dist-info/METADATA
template_forge-1.0.0.dist-info/WHEEL
template_forge-1.0.0.dist-info/entry_points.txt
template_forge-1.0.0.dist-info/licenses/LICENSE
template_forge-1.0.0.dist-info/RECORD
