Metadata-Version: 2.4
Name: template-forge
Version: 1.0.0
Summary: Transform structured data (JSON/YAML/XML) into code, configs, and docs with Jinja2 templates
Project-URL: Homepage, https://github.com/CarloFornari/template_forge
Project-URL: Documentation, https://github.com/CarloFornari/template_forge/blob/main/docs/README.md
Project-URL: Quickstart, https://github.com/CarloFornari/template_forge/blob/main/QUICKSTART.md
Project-URL: Bug Reports, https://github.com/CarloFornari/template_forge/issues
Project-URL: Source, https://github.com/CarloFornari/template_forge
Project-URL: Changelog, https://github.com/CarloFornari/template_forge/releases
Author-email: Carlo Fornari <carlo.fornari@example.com>
License: MIT
License-File: LICENSE
Keywords: arxml,automation,autosar,boilerplate,code-generation,code-generator,configuration,jinja2,json,scaffolding,template,xml,yaml
Classifier: Development Status :: 5 - Production/Stable
Classifier: Environment :: Console
Classifier: Intended Audience :: Developers
Classifier: License :: OSI Approved :: MIT License
Classifier: Operating System :: OS Independent
Classifier: Programming Language :: Python :: 3
Classifier: Programming Language :: Python :: 3.8
Classifier: Programming Language :: Python :: 3.9
Classifier: Programming Language :: Python :: 3.10
Classifier: Programming Language :: Python :: 3.11
Classifier: Programming Language :: Python :: 3.12
Classifier: Topic :: Software Development :: Build Tools
Classifier: Topic :: Software Development :: Code Generators
Classifier: Topic :: Text Processing :: Markup
Classifier: Typing :: Typed
Requires-Python: >=3.8
Requires-Dist: defusedxml>=0.7.1
Requires-Dist: jinja2>=3.1.2
Requires-Dist: pyyaml>=6.0.1
Provides-Extra: dev
Requires-Dist: bandit[toml]>=1.7.5; extra == 'dev'
Requires-Dist: build>=1.0.0; extra == 'dev'
Requires-Dist: coverage>=7.0.0; extra == 'dev'
Requires-Dist: mypy>=1.6.0; extra == 'dev'
Requires-Dist: pre-commit>=3.5.0; extra == 'dev'
Requires-Dist: pytest-cov>=4.1.0; extra == 'dev'
Requires-Dist: pytest>=7.4.0; extra == 'dev'
Requires-Dist: ruff>=0.1.0; extra == 'dev'
Requires-Dist: safety>=2.3.0; extra == 'dev'
Requires-Dist: twine>=4.0.0; extra == 'dev'
Provides-Extra: docs
Requires-Dist: mkdocs-material>=9.4.0; extra == 'docs'
Requires-Dist: mkdocs>=1.5.0; extra == 'docs'
Requires-Dist: mkdocstrings[python]>=0.23.0; extra == 'docs'
Provides-Extra: testing
Requires-Dist: coverage>=7.0.0; extra == 'testing'
Requires-Dist: pytest-cov>=4.1.0; extra == 'testing'
Requires-Dist: pytest>=7.4.0; extra == 'testing'
